ovos_skill_word_of_the_day/LICENSE
ovos_skill_word_of_the_day/README.md
ovos_skill_word_of_the_day/__init__.py
ovos_skill_word_of_the_day/version.py
ovos_skill_word_of_the_day/locale/ca/WordOfTheDayKeyword.voc
ovos_skill_word_of_the_day/locale/ca/unknown.wod.dialog
ovos_skill_word_of_the_day/locale/ca/word.of.day.dialog
ovos_skill_word_of_the_day/locale/da/WordOfTheDayKeyword.voc
ovos_skill_word_of_the_day/locale/da/unknown.wod.dialog
ovos_skill_word_of_the_day/locale/da/word.of.day.dialog
ovos_skill_word_of_the_day/locale/de/WordOfTheDayKeyword.voc
ovos_skill_word_of_the_day/locale/de/unknown.wod.dialog
ovos_skill_word_of_the_day/locale/de/word.of.day.dialog
ovos_skill_word_of_the_day/locale/en-us/WordOfTheDayKeyword.voc
ovos_skill_word_of_the_day/locale/en-us/unknown.wod.dialog
ovos_skill_word_of_the_day/locale/en-us/word.of.day.dialog
ovos_skill_word_of_the_day/locale/gl/unknown.wod.dialog
ovos_skill_word_of_the_day/locale/gl/word.of.day.dialog
ovos_skill_word_of_the_day/locale/pt-pt/WordOfTheDayKeyword.voc
ovos_skill_word_of_the_day/locale/pt-pt/unknown.wod.dialog
ovos_skill_word_of_the_day/locale/pt-pt/word.of.day.dialog
ovos_skill_word_of_the_day/ovos_skill_word_of_the_day.egg-info/PKG-INFO
ovos_skill_word_of_the_day/ovos_skill_word_of_the_day.egg-info/SOURCES.txt
ovos_skill_word_of_the_day/ovos_skill_word_of_the_day.egg-info/dependency_links.txt
ovos_skill_word_of_the_day/ovos_skill_word_of_the_day.egg-info/entry_points.txt
ovos_skill_word_of_the_day/ovos_skill_word_of_the_day.egg-info/requires.txt
ovos_skill_word_of_the_day/ovos_skill_word_of_the_day.egg-info/top_level.txt
ovos_skill_word_of_the_day-0.2.0.dist-info/LICENSE
ovos_skill_word_of_the_day-0.2.0.dist-info/METADATA
ovos_skill_word_of_the_day-0.2.0.dist-info/WHEEL
ovos_skill_word_of_the_day-0.2.0.dist-info/entry_points.txt
ovos_skill_word_of_the_day-0.2.0.dist-info/top_level.txt
ovos_skill_word_of_the_day-0.2.0.dist-info/RECORD
