Metadata-Version: 2.1
Name: ovos-skill-word-of-the-day
Version: 0.2.0
Summary: WordOfTheDaySkill
Home-page: https://github.com/OpenVoiceOS/ovos-skill-word-of-the-day
Author: OpenVoiceOS
Author-email: 
License: Apache2.0
Keywords: ovos skill plugin
License-File: LICENSE
Requires-Dist: requests
Requires-Dist: bs4
Requires-Dist: ovos-workshop
